pelican/plugins/thumbnailer/__init__.py
pelican/plugins/thumbnailer/test_thumbnails.py
pelican/plugins/thumbnailer/thumbnailer.py
pelican_thumbnailer-1.0.2.dist-info/METADATA
pelican_thumbnailer-1.0.2.dist-info/WHEEL
pelican_thumbnailer-1.0.2.dist-info/RECORD
