Metadata-Version: 2.1
Name: pelican-thumbnailer
Version: 1.0.2
Summary: Thumbnailer is a Pelican plugin creates smaller versions of images found in a directory
Keywords: pelican plugin image thumbnail picture Pillow resize
Author-Email: Justin Mayer <entroP@gmail.com>, Kevin Deldycke <kevin@deldycke.com>
License: AGPL-3.0
Classifier: Development Status :: 5 - Production/Stable
Classifier: Environment :: Console
Classifier: Framework :: Pelican
Classifier: Framework :: Pelican :: Plugins
Classifier: Intended Audience :: End Users/Desktop
Classifier: License :: OSI Approved :: GNU Affero General Public License v3 or later (AGPLv3+)
Classifier: Operating System :: OS Independent
Classifier: Programming Language :: Python :: 3
Classifier: Programming Language :: Python :: 3.8
Classifier: Programming Language :: Python :: 3.9
Classifier: Programming Language :: Python :: 3.10
Classifier: Programming Language :: Python :: 3.11
Classifier: Programming Language :: Python :: 3.12
Classifier: Topic :: Internet :: WWW/HTTP
Classifier: Topic :: Software Development :: Libraries :: Python Modules
Project-URL: Homepage, https://github.com/pelican-plugins/thumbnailer
Project-URL: Funding, https://donate.getpelican.com/
Project-URL: Issue tracker, https://github.com/pelican-plugins/thumbnailer/issues
Requires-Python: <4.0,>=3.8.1
Requires-Dist: pelican>=4.5
Requires-Dist: Pillow>=9.5
